KuulKaggleTools/__init__.py
KuulKaggleTools/enums.py
KuulKaggleTools/utils.py
KuulKaggleTools/mode_splitter/__init__.py
KuulKaggleTools/mode_splitter/eda.py
KuulKaggleTools/mode_splitter/enums.py
KuulKaggleTools/mode_splitter/tests.py
KuulKaggleTools/mode_splitter/utils.py
KuulKaggleTools/nn/__init__.py
KuulKaggleTools/nn/train/AE.py
KuulKaggleTools/nn/train/__init__.py
KuulKaggleTools/nn/train/utils.py
KuulKaggleTools/vis/__init__.py
KuulKaggleTools-0.0.6.dist-info/LICENSE
KuulKaggleTools-0.0.6.dist-info/METADATA
KuulKaggleTools-0.0.6.dist-info/WHEEL
KuulKaggleTools-0.0.6.dist-info/top_level.txt
KuulKaggleTools-0.0.6.dist-info/RECORD
