Metadata-Version: 2.1
Name: KuulKaggleTools
Version: 0.0.6
Summary: Just some kuul Kaggle tools I like to use
Home-page: https://github.com/tedtroxell/KaggleTools
Author: Ted Troxell
Author-email: ted@tedtroxell.com
License: UNKNOWN
Project-URL: Bug Tracker, https://github.com/tedtroxell/KaggleTools/issues
Platform: UNKNOWN
Classifier: Programming Language :: Python :: 3
Classifier: License :: OSI Approved :: MIT License
Classifier: Operating System :: OS Independent
Requires-Python: >=3.6
